Workbook

Sheet Clientes
A1: CADASTRO DE CLIENTES
A2: Penumper | B2: Nome | C2: CPF

Sheet Aplicacoes
A1: BASE DE APLICAÇÕES — POSIÇÃO ATUAL
A2: Penumper | B2: Mês (AAAAMM) | C2: Produto | D2: Subproduto | E2: Vencimento | F2: Saldo Ponta | G2: Idade | H2: Nome (automático) | I2: CPF (automático) | J2: rk
H3: =IF($A3="","",IFERROR(VLOOKUP($A3,Clientes!$A$3:$C$1002,2,0),"NÃO CADASTRADO")) | I3: =IF($A3="","",IFERROR(VLOOKUP($A3,Clientes!$A$3:$C$1002,3,0),"NÃO CADASTRADO")) | J3: =IF($A3="","",IF($A3='Carteira do Cliente'!$B$4,COUNTIF($A$3:$A3,'Carteira do Cliente'!$B$4),""))
H4: =IF($A4="","",IFERROR(VLOOKUP($A4,Clientes!$A$3:$C$1002,2,0),"NÃO CADASTRADO")) | I4: =IF($A4="","",IFERROR(VLOOKUP($A4,Clientes!$A$3:$C$1002,3,0),"NÃO CADASTRADO")) | J4: =IF($A4="","",IF($A4='Carteira do Cliente'!$B$4,COUNTIF($A$3:$A4,'Carteira do Cliente'!$B$4),""))
H5: =IF($A5="","",IFERROR(VLOOKUP($A5,Clientes!$A$3:$C$1002,2,0),"NÃO CADASTRADO")) | I5: =IF($A5="","",IFERROR(VLOOKUP($A5,Clientes!$A$3:$C$1002,3,0),"NÃO CADASTRADO")) | J5: =IF($A5="","",IF($A5='Carteira do Cliente'!$B$4,COUNTIF($A$3:$A5,'Carteira do Cliente'!$B$4),""))
H6: =IF($A6="","",IFERROR(VLOOKUP($A6,Clientes!$A$3:$C$1002,2,0),"NÃO CADASTRADO")) | I6: =IF($A6="","",IFERROR(VLOOKUP($A6,Clientes!$A$3:$C$1002,3,0),"NÃO CADASTRADO")) | J6: =IF($A6="","",IF($A6='Carteira do Cliente'!$B$4,COUNTIF($A$3:$A6,'Carteira do Cliente'!$B$4),""))
H7: =IF($A7="","",IFERROR(VLOOKUP($A7,Clientes!$A$3:$C$1002,2,0),"NÃO CADASTRADO")) | I7: =IF($A7="","",IFERROR(VLOOKUP($A7,Clientes!$A$3:$C$1002,3,0),"NÃO CADASTRADO")) | J7: =IF($A7="","",IF($A7='Carteira do Cliente'!$B$4,COUNTIF($A$3:$A7,'Carteira do Cliente'!$B$4),""))
H8: =IF($A8="","",IFERROR(VLOOKUP($A8,Clientes!$A$3:$C$1002,2,0),"NÃO CADASTRADO")) | I8: =IF($A8="","",IFERROR(VLOOKUP($A8,Clientes!$A$3:$C$1002,3,0),"NÃO CADASTRADO")) | J8: =IF($A8="","",IF($A8='Carteira do Cliente'!$B$4,COUNTIF($A$3:$A8,'Carteira do Cliente'!$B$4),""))
H9: =IF($A9="","",IFERROR(VLOOKUP($A9,Clientes!$A$3:$C$1002,2,0),"NÃO CADASTRADO")) | I9: =IF($A9="","",IFERROR(VLOOKUP($A9,Clientes!$A$3:$C$1002,3,0),"NÃO CADASTRADO")) | J9: =IF($A9="","",IF($A9='Carteira do Cliente'!$B$4,COUNTIF($A$3:$A9,'Carteira do Cliente'!$B$4),""))
H10: =IF($A10="","",IFERROR(VLOOKUP($A10,Clientes!$A$3:$C$1002,2,0),"NÃO CADASTRADO")) | I10: =IF($A10="","",IFERROR(VLOOKUP($A10,Clientes!$A$3:$C$1002,3,0),"NÃO CADASTRADO")) | J10: =IF($A10="","",IF($A10='Carteira do Cliente'!$B$4,COUNTIF($A$3:$A10,'Carteira do Cliente'!$B$4),""))
H11: =IF($A11="","",IFERROR(VLOOKUP($A11,Clientes!$A$3:$C$1002,2,0),"NÃO CADASTRADO")) | I11: =IF($A11="","",IFERROR(VLOOKUP($A11,Clientes!$A$3:$C$1002,3,0),"NÃO CADASTRADO")) | J11: =IF($A11="","",IF($A11='Carteira do Cliente'!$B$4,COUNTIF($A$3:$A11,'Carteira do Cliente'!$B$4),""))
H12: =IF($A12="","",IFERROR(VLOOKUP($A12,Clientes!$A$3:$C$1002,2,0),"NÃO CADASTRADO")) | I12: =IF($A12="","",IFERROR(VLOOKUP($A12,Clientes!$A$3:$C$1002,3,0),"NÃO CADASTRADO")) | J12: =IF($A12="","",IF($A12='Carteira do Cliente'!$B$4,COUNTIF($A$3:$A12,'Carteira do Cliente'!$B$4),""))
H13: =IF($A13="","",IFERROR(VLOOKUP($A13,Clientes!$A$3:$C$1002,2,0),"NÃO CADASTRADO")) | I13: =IF($A13="","",IFERROR(VLOOKUP($A13,Clientes!$A$3:$C$1002,3,0),"NÃO CADASTRADO")) | J13: =IF($A13="","",IF($A13='Carteira do Cliente'!$B$4,COUNTIF($A$3:$A13,'Carteira do Cliente'!$B$4),""))
H14: =IF($A14="","",IFERROR(VLOOKUP($A14,Clientes!$A$3:$C$1002,2,0),"NÃO CADASTRADO")) | I14: =IF($A14="","",IFERROR(VLOOKUP($A14,Clientes!$A$3:$C$1002,3,0),"NÃO CADASTRADO")) | J14: =IF($A14="","",IF($A14='Carteira do Cliente'!$B$4,COUNTIF($A$3:$A14,'Carteira do Cliente'!$B$4),""))
... H1002: =IF($A1002="","",IFERROR(VLOOKUP($A1002,Clientes!$A$3:$C$1002,2,0),"NÃO CADASTRADO")) | I1002: =IF($A1002="","",IFERROR(VLOOKUP($A1002,Clientes!$A$3:$C$1002,3,0),"NÃO CADASTRADO")) | J1002: =IF($A1002="","",IF($A1002='Carteira do Cliente'!$B$4,COUNTIF($A$3:$A1002,'Carteira do Cliente'!$B$4),""))

Sheet Carteira do Cliente
A1: CARTEIRA DO CLIENTE — POSIÇÃO ATUAL
A3: Cliente:
A4: Penumper: | B4: =IFERROR(INDEX(Clientes!$A$3:$A$1002,MATCH($B$3,Clientes!$B$3:$B$1002,0)),"")
A5: CPF: | B5: =IFERROR(INDEX(Clientes!$C$3:$C$1002,MATCH($B$3,Clientes!$B$3:$B$1002,0)),"")
A6: Patrimônio total: | B6: =SUMIFS(Aplicacoes!$F$3:$F$1002,Aplicacoes!$A$3:$A$1002,$B$4)
A7: Nº de aplicações: | B7: =COUNTIF(Aplicacoes!$A$3:$A$1002,$B$4)
A9: ALOCAÇÃO POR PRODUTO / CLASSE
A10: Classe | B10: Filtro (contém) | C10: Saldo (R$) | D10: % da carteira
A11: Fundos | B11: FUNDOS | C11: =IF($B11="",0,SUMIFS(Aplicacoes!$F$3:$F$1002,Aplicacoes!$A$3:$A$1002,$B$4,Aplicacoes!$C$3:$C$1002,"*"&$B11&"*")) | D11: =IFERROR($C11/$B$6,0)
A12: Crédito Privado | B12: CRED | C12: =IF($B12="",0,SUMIFS(Aplicacoes!$F$3:$F$1002,Aplicacoes!$A$3:$A$1002,$B$4,Aplicacoes!$C$3:$C$1002,"*"&$B12&"*")) | D12: =IFERROR($C12/$B$6,0)
A13: Letras (LCI/LCA) | B13: LETRAS | C13: =IF($B13="",0,SUMIFS(Aplicacoes!$F$3:$F$1002,Aplicacoes!$A$3:$A$1002,$B$4,Aplicacoes!$C$3:$C$1002,"*"&$B13&"*")) | D13: =IFERROR($C13/$B$6,0)
A14: CDB | B14: CDB | C14: =IF($B14="",0,SUMIFS(Aplicacoes!$F$3:$F$1002,Aplicacoes!$A$3:$A$1002,$B$4,Aplicacoes!$C$3:$C$1002,"*"&$B14&"*")) | D14: =IFERROR($C14/$B$6,0)
A15: LCA (emissor direto) | B15: LCA | C15: =IF($B15="",0,SUMIFS(Aplicacoes!$F$3:$F$1002,Aplicacoes!$A$3:$A$1002,$B$4,Aplicacoes!$C$3:$C$1002,"*"&$B15&"*")) | D15: =IFERROR($C15/$B$6,0)
A16: Tesouraria / Outros | B16: TESOURARIA | C16: =IF($B16="",0,SUMIFS(Aplicacoes!$F$3:$F$1002,Aplicacoes!$A$3:$A$1002,$B$4,Aplicacoes!$C$3:$C$1002,"*"&$B16&"*")) | D16: =IFERROR($C16/$B$6,0)
C17: =IF($B17="",0,SUMIFS(Aplicacoes!$F$3:$F$1002,Aplicacoes!$A$3:$A$1002,$B$4,Aplicacoes!$C$3:$C$1002,"*"&$B17&"*")) | D17: =IFERROR($C17/$B$6,0)
C18: =IF($B18="",0,SUMIFS(Aplicacoes!$F$3:$F$1002,Aplicacoes!$A$3:$A$1002,$B$4,Aplicacoes!$C$3:$C$1002,"*"&$B18&"*")) | D18: =IFERROR($C18/$B$6,0)
A19: TOTAL CLASSIFICADO | C19: =SUM(C11:C18) | D19: =SUM(D11:D18)
A20: Não classificado | C20: =$B$6-$C$19 | D20: =IFERROR($C20/$B$6,0)
A22: APLICAÇÕES DO CLIENTE
A23: Produto | B23: Subproduto | C23: Vencimento | D23: Saldo (R$) | E23: % carteira | F23: Idade
A24: =IFERROR(INDEX(Aplicacoes!$C$3:$C$1002,MATCH(1,Aplicacoes!$J$3:$J$1002,0)),"") | B24: =IFERROR(INDEX(Aplicacoes!$D$3:$D$1002,MATCH(1,Aplicacoes!$J$3:$J$1002,0)),"") | C24: =IFERROR(INDEX(Aplicacoes!$E$3:$E$1002,MATCH(1,Aplicacoes!$J$3:$J$1002,0)),"") | D24: =IFERROR(INDEX(Aplicacoes!$F$3:$F$1002,MATCH(1,Aplicacoes!$J$3:$J$1002,0)),"") | E24: =IFERROR(INDEX(Aplicacoes!$F$3:$F$1002,MATCH(1,Aplicacoes!$J$3:$J$1002,0))/$B$6,"") | F24: =IFERROR(INDEX(Aplicacoes!$G$3:$G$1002,MATCH(1,Aplicacoes!$J$3:$J$1002,0)),"")
A25: =IFERROR(INDEX(Aplicacoes!$C$3:$C$1002,MATCH(2,Aplicacoes!$J$3:$J$1002,0)),"") | B25: =IFERROR(INDEX(Aplicacoes!$D$3:$D$1002,MATCH(2,Aplicacoes!$J$3:$J$1002,0)),"") | C25: =IFERROR(INDEX(Aplicacoes!$E$3:$E$1002,MATCH(2,Aplicacoes!$J$3:$J$1002,0)),"") | D25: =IFERROR(INDEX(Aplicacoes!$F$3:$F$1002,MATCH(2,Aplicacoes!$J$3:$J$1002,0)),"") | E25: =IFERROR(INDEX(Aplicacoes!$F$3:$F$1002,MATCH(2,Aplicacoes!$J$3:$J$1002,0))/$B$6,"") | F25: =IFERROR(INDEX(Aplicacoes!$G$3:$G$1002,MATCH(2,Aplicacoes!$J$3:$J$1002,0)),"")
A26: =IFERROR(INDEX(Aplicacoes!$C$3:$C$1002,MATCH(3,Aplicacoes!$J$3:$J$1002,0)),"") | B26: =IFERROR(INDEX(Aplicacoes!$D$3:$D$1002,MATCH(3,Aplicacoes!$J$3:$J$1002,0)),"") | C26: =IFERROR(INDEX(Aplicacoes!$E$3:$E$1002,MATCH(3,Aplicacoes!$J$3:$J$1002,0)),"") | D26: =IFERROR(INDEX(Aplicacoes!$F$3:$F$1002,MATCH(3,Aplicacoes!$J$3:$J$1002,0)),"") | E26: =IFERROR(INDEX(Aplicacoes!$F$3:$F$1002,MATCH(3,Aplicacoes!$J$3:$J$1002,0))/$B$6,"") | F26: =IFERROR(INDEX(Aplicacoes!$G$3:$G$1002,MATCH(3,Aplicacoes!$J$3:$J$1002,0)),"")
A27: =IFERROR(INDEX(Aplicacoes!$C$3:$C$1002,MATCH(4,Aplicacoes!$J$3:$J$1002,0)),"") | B27: =IFERROR(INDEX(Aplicacoes!$D$3:$D$1002,MATCH(4,Aplicacoes!$J$3:$J$1002,0)),"") | C27: =IFERROR(INDEX(Aplicacoes!$E$3:$E$1002,MATCH(4,Aplicacoes!$J$3:$J$1002,0)),"") | D27: =IFERROR(INDEX(Aplicacoes!$F$3:$F$1002,MATCH(4,Aplicacoes!$J$3:$J$1002,0)),"") | E27: =IFERROR(INDEX(Aplicacoes!$F$3:$F$1002,MATCH(4,Aplicacoes!$J$3:$J$1002,0))/$B$6,"") | F27: =IFERROR(INDEX(Aplicacoes!$G$3:$G$1002,MATCH(4,Aplicacoes!$J$3:$J$1002,0)),"")
A28: =IFERROR(INDEX(Aplicacoes!$C$3:$C$1002,MATCH(5,Aplicacoes!$J$3:$J$1002,0)),"") | B28: =IFERROR(INDEX(Aplicacoes!$D$3:$D$1002,MATCH(5,Aplicacoes!$J$3:$J$1002,0)),"") | C28: =IFERROR(INDEX(Aplicacoes!$E$3:$E$1002,MATCH(5,Aplicacoes!$J$3:$J$1002,0)),"") | D28: =IFERROR(INDEX(Aplicacoes!$F$3:$F$1002,MATCH(5,Aplicacoes!$J$3:$J$1002,0)),"") | E28: =IFERROR(INDEX(Aplicacoes!$F$3:$F$1002,MATCH(5,Aplicacoes!$J$3:$J$1002,0))/$B$6,"") | F28: =IFERROR(INDEX(Aplicacoes!$G$3:$G$1002,MATCH(5,Aplicacoes!$J$3:$J$1002,0)),"")
A29: =IFERROR(INDEX(Aplicacoes!$C$3:$C$1002,MATCH(6,Aplicacoes!$J$3:$J$1002,0)),"") | B29: =IFERROR(INDEX(Aplicacoes!$D$3:$D$1002,MATCH(6,Aplicacoes!$J$3:$J$1002,0)),"") | C29: =IFERROR(INDEX(Aplicacoes!$E$3:$E$1002,MATCH(6,Aplicacoes!$J$3:$J$1002,0)),"") | D29: =IFERROR(INDEX(Aplicacoes!$F$3:$F$1002,MATCH(6,Aplicacoes!$J$3:$J$1002,0)),"") | E29: =IFERROR(INDEX(Aplicacoes!$F$3:$F$1002,MATCH(6,Aplicacoes!$J$3:$J$1002,0))/$B$6,"") | F29: =IFERROR(INDEX(Aplicacoes!$G$3:$G$1002,MATCH(6,Aplicacoes!$J$3:$J$1002,0)),"")
A30: =IFERROR(INDEX(Aplicacoes!$C$3:$C$1002,MATCH(7,Aplicacoes!$J$3:$J$1002,0)),"") | B30: =IFERROR(INDEX(Aplicacoes!$D$3:$D$1002,MATCH(7,Aplicacoes!$J$3:$J$1002,0)),"") | C30: =IFERROR(INDEX(Aplicacoes!$E$3:$E$1002,MATCH(7,Aplicacoes!$J$3:$J$1002,0)),"") | D30: =IFERROR(INDEX(Aplicacoes!$F$3:$F$1002,MATCH(7,Aplicacoes!$J$3:$J$1002,0)),"") | E30: =IFERROR(INDEX(Aplicacoes!$F$3:$F$1002,MATCH(7,Aplicacoes!$J$3:$J$1002,0))/$B$6,"") | F30: =IFERROR(INDEX(Aplicacoes!$G$3:$G$1002,MATCH(7,Aplicacoes!$J$3:$J$1002,0)),"")
A31: =IFERROR(INDEX(Aplicacoes!$C$3:$C$1002,MATCH(8,Aplicacoes!$J$3:$J$1002,0)),"") | B31: =IFERROR(INDEX(Aplicacoes!$D$3:$D$1002,MATCH(8,Aplicacoes!$J$3:$J$1002,0)),"") | C31: =IFERROR(INDEX(Aplicacoes!$E$3:$E$1002,MATCH(8,Aplicacoes!$J$3:$J$1002,0)),"") | D31: =IFERROR(INDEX(Aplicacoes!$F$3:$F$1002,MATCH(8,Aplicacoes!$J$3:$J$1002,0)),"") | E31: =IFERROR(INDEX(Aplicacoes!$F$3:$F$1002,MATCH(8,Aplicacoes!$J$3:$J$1002,0))/$B$6,"") | F31: =IFERROR(INDEX(Aplicacoes!$G$3:$G$1002,MATCH(8,Aplicacoes!$J$3:$J$1002,0)),"")
A32: =IFERROR(INDEX(Aplicacoes!$C$3:$C$1002,MATCH(9,Aplicacoes!$J$3:$J$1002,0)),"") | B32: =IFERROR(INDEX(Aplicacoes!$D$3:$D$1002,MATCH(9,Aplicacoes!$J$3:$J$1002,0)),"") | C32: =IFERROR(INDEX(Aplicacoes!$E$3:$E$1002,MATCH(9,Aplicacoes!$J$3:$J$1002,0)),"") | D32: =IFERROR(INDEX(Aplicacoes!$F$3:$F$1002,MATCH(9,Aplicacoes!$J$3:$J$1002,0)),"") | E32: =IFERROR(INDEX(Aplicacoes!$F$3:$F$1002,MATCH(9,Aplicacoes!$J$3:$J$1002,0))/$B$6,"") | F32: =IFERROR(INDEX(Aplicacoes!$G$3:$G$1002,MATCH(9,Aplicacoes!$J$3:$J$1002,0)),"")
A33: =IFERROR(INDEX(Aplicacoes!$C$3:$C$1002,MATCH(10,Aplicacoes!$J$3:$J$1002,0)),"") | B33: =IFERROR(INDEX(Aplicacoes!$D$3:$D$1002,MATCH(10,Aplicacoes!$J$3:$J$1002,0)),"") | C33: =IFERROR(INDEX(Aplicacoes!$E$3:$E$1002,MATCH(10,Aplicacoes!$J$3:$J$1002,0)),"") | D33: =IFERROR(INDEX(Aplicacoes!$F$3:$F$1002,MATCH(10,Aplicacoes!$J$3:$J$1002,0)),"") | E33: =IFERROR(INDEX(Aplicacoes!$F$3:$F$1002,MATCH(10,Aplicacoes!$J$3:$J$1002,0))/$B$6,"") | F33: =IFERROR(INDEX(Aplicacoes!$G$3:$G$1002,MATCH(10,Aplicacoes!$J$3:$J$1002,0)),"")
A34: =IFERROR(INDEX(Aplicacoes!$C$3:$C$1002,MATCH(11,Aplicacoes!$J$3:$J$1002,0)),"") | B34: =IFERROR(INDEX(Aplicacoes!$D$3:$D$1002,MATCH(11,Aplicacoes!$J$3:$J$1002,0)),"") | C34: =IFERROR(INDEX(Aplicacoes!$E$3:$E$1002,MATCH(11,Aplicacoes!$J$3:$J$1002,0)),"") | D34: =IFERROR(INDEX(Aplicacoes!$F$3:$F$1002,MATCH(11,Aplicacoes!$J$3:$J$1002,0)),"") | E34: =IFERROR(INDEX(Aplicacoes!$F$3:$F$1002,MATCH(11,Aplicacoes!$J$3:$J$1002,0))/$B$6,"") | F34: =IFERROR(INDEX(Aplicacoes!$G$3:$G$1002,MATCH(11,Aplicacoes!$J$3:$J$1002,0)),"")
A35: =IFERROR(INDEX(Aplicacoes!$C$3:$C$1002,MATCH(12,Aplicacoes!$J$3:$J$1002,0)),"") | B35: =IFERROR(INDEX(Aplicacoes!$D$3:$D$1002,MATCH(12,Aplicacoes!$J$3:$J$1002,0)),"") | C35: =IFERROR(INDEX(Aplicacoes!$E$3:$E$1002,MATCH(12,Aplicacoes!$J$3:$J$1002,0)),"") | D35: =IFERROR(INDEX(Aplicacoes!$F$3:$F$1002,MATCH(12,Aplicacoes!$J$3:$J$1002,0)),"") | E35: =IFERROR(INDEX(Aplicacoes!$F$3:$F$1002,MATCH(12,Aplicacoes!$J$3:$J$1002,0))/$B$6,"") | F35: =IFERROR(INDEX(Aplicacoes!$G$3:$G$1002,MATCH(12,Aplicacoes!$J$3:$J$1002,0)),"")
A36: =IFERROR(INDEX(Aplicacoes!$C$3:$C$1002,MATCH(13,Aplicacoes!$J$3:$J$1002,0)),"") | B36: =IFERROR(INDEX(Aplicacoes!$D$3:$D$1002,MATCH(13,Aplicacoes!$J$3:$J$1002,0)),"") | C36: =IFERROR(INDEX(Aplicacoes!$E$3:$E$1002,MATCH(13,Aplicacoes!$J$3:$J$1002,0)),"") | D36: =IFERROR(INDEX(Aplicacoes!$F$3:$F$1002,MATCH(13,Aplicacoes!$J$3:$J$1002,0)),"") | E36: =IFERROR(INDEX(Aplicacoes!$F$3:$F$1002,MATCH(13,Aplicacoes!$J$3:$J$1002,0))/$B$6,"") | F36: =IFERROR(INDEX(Aplicacoes!$G$3:$G$1002,MATCH(13,Aplicacoes!$J$3:$J$1002,0)),"")
A37: =IFERROR(INDEX(Aplicacoes!$C$3:$C$1002,MATCH(14,Aplicacoes!$J$3:$J$1002,0)),"") | B37: =IFERROR(INDEX(Aplicacoes!$D$3:$D$1002,MATCH(14,Aplicacoes!$J$3:$J$1002,0)),"") | C37: =IFERROR(INDEX(Aplicacoes!$E$3:$E$1002,MATCH(14,Aplicacoes!$J$3:$J$1002,0)),"") | D37: =IFERROR(INDEX(Aplicacoes!$F$3:$F$1002,MATCH(14,Aplicacoes!$J$3:$J$1002,0)),"") | E37: =IFERROR(INDEX(Aplicacoes!$F$3:$F$1002,MATCH(14,Aplicacoes!$J$3:$J$1002,0))/$B$6,"") | F37: =IFERROR(INDEX(Aplicacoes!$G$3:$G$1002,MATCH(14,Aplicacoes!$J$3:$J$1002,0)),"")
A38: =IFERROR(INDEX(Aplicacoes!$C$3:$C$1002,MATCH(15,Aplicacoes!$J$3:$J$1002,0)),"") | B38: =IFERROR(INDEX(Aplicacoes!$D$3:$D$1002,MATCH(15,Aplicacoes!$J$3:$J$1002,0)),"") | C38: =IFERROR(INDEX(Aplicacoes!$E$3:$E$1002,MATCH(15,Aplicacoes!$J$3:$J$1002,0)),"") | D38: =IFERROR(INDEX(Aplicacoes!$F$3:$F$1002,MATCH(15,Aplicacoes!$J$3:$J$1002,0)),"") | E38: =IFERROR(INDEX(Aplicacoes!$F$3:$F$1002,MATCH(15,Aplicacoes!$J$3:$J$1002,0))/$B$6,"") | F38: =IFERROR(INDEX(Aplicacoes!$G$3:$G$1002,MATCH(15,Aplicacoes!$J$3:$J$1002,0)),"")
A39: =IFERROR(INDEX(Aplicacoes!$C$3:$C$1002,MATCH(16,Aplicacoes!$J$3:$J$1002,0)),"") | B39: =IFERROR(INDEX(Aplicacoes!$D$3:$D$1002,MATCH(16,Aplicacoes!$J$3:$J$1002,0)),"") | C39: =IFERROR(INDEX(Aplicacoes!$E$3:$E$1002,MATCH(16,Aplicacoes!$J$3:$J$1002,0)),"") | D39: =IFERROR(INDEX(Aplicacoes!$F$3:$F$1002,MATCH(16,Aplicacoes!$J$3:$J$1002,0)),"") | E39: =IFERROR(INDEX(Aplicacoes!$F$3:$F$1002,MATCH(16,Aplicacoes!$J$3:$J$1002,0))/$B$6,"") | F39: =IFERROR(INDEX(Aplicacoes!$G$3:$G$1002,MATCH(16,Aplicacoes!$J$3:$J$1002,0)),"")
A40: =IFERROR(INDEX(Aplicacoes!$C$3:$C$1002,MATCH(17,Aplicacoes!$J$3:$J$1002,0)),"") | B40: =IFERROR(INDEX(Aplicacoes!$D$3:$D$1002,MATCH(17,Aplicacoes!$J$3:$J$1002,0)),"") | C40: =IFERROR(INDEX(Aplicacoes!$E$3:$E$1002,MATCH(17,Aplicacoes!$J$3:$J$1002,0)),"") | D40: =IFERROR(INDEX(Aplicacoes!$F$3:$F$1002,MATCH(17,Aplicacoes!$J$3:$J$1002,0)),"") | E40: =IFERROR(INDEX(Aplicacoes!$F$3:$F$1002,MATCH(17,Aplicacoes!$J$3:$J$1002,0))/$B$6,"") | F40: =IFERROR(INDEX(Aplicacoes!$G$3:$G$1002,MATCH(17,Aplicacoes!$J$3:$J$1002,0)),"")
A41: =IFERROR(INDEX(Aplicacoes!$C$3:$C$1002,MATCH(18,Aplicacoes!$J$3:$J$1002,0)),"") | B41: =IFERROR(INDEX(Aplicacoes!$D$3:$D$1002,MATCH(18,Aplicacoes!$J$3:$J$1002,0)),"") | C41: =IFERROR(INDEX(Aplicacoes!$E$3:$E$1002,MATCH(18,Aplicacoes!$J$3:$J$1002,0)),"") | D41: =IFERROR(INDEX(Aplicacoes!$F$3:$F$1002,MATCH(18,Aplicacoes!$J$3:$J$1002,0)),"") | E41: =IFERROR(INDEX(Aplicacoes!$F$3:$F$1002,MATCH(18,Aplicacoes!$J$3:$J$1002,0))/$B$6,"") | F41: =IFERROR(INDEX(Aplicacoes!$G$3:$G$1002,MATCH(18,Aplicacoes!$J$3:$J$1002,0)),"")
A42: =IFERROR(INDEX(Aplicacoes!$C$3:$C$1002,MATCH(19,Aplicacoes!$J$3:$J$1002,0)),"") | B42: =IFERROR(INDEX(Aplicacoes!$D$3:$D$1002,MATCH(19,Aplicacoes!$J$3:$J$1002,0)),"") | C42: =IFERROR(INDEX(Aplicacoes!$E$3:$E$1002,MATCH(19,Aplicacoes!$J$3:$J$1002,0)),"") | D42: =IFERROR(INDEX(Aplicacoes!$F$3:$F$1002,MATCH(19,Aplicacoes!$J$3:$J$1002,0)),"") | E42: =IFERROR(INDEX(Aplicacoes!$F$3:$F$1002,MATCH(19,Aplicacoes!$J$3:$J$1002,0))/$B$6,"") | F42: =IFERROR(INDEX(Aplicacoes!$G$3:$G$1002,MATCH(19,Aplicacoes!$J$3:$J$1002,0)),"")
A43: =IFERROR(INDEX(Aplicacoes!$C$3:$C$1002,MATCH(20,Aplicacoes!$J$3:$J$1002,0)),"") | B43: =IFERROR(INDEX(Aplicacoes!$D$3:$D$1002,MATCH(20,Aplicacoes!$J$3:$J$1002,0)),"") | C43: =IFERROR(INDEX(Aplicacoes!$E$3:$E$1002,MATCH(20,Aplicacoes!$J$3:$J$1002,0)),"") | D43: =IFERROR(INDEX(Aplicacoes!$F$3:$F$1002,MATCH(20,Aplicacoes!$J$3:$J$1002,0)),"") | E43: =IFERROR(INDEX(Aplicacoes!$F$3:$F$1002,MATCH(20,Aplicacoes!$J$3:$J$1002,0))/$B$6,"") | F43: =IFERROR(INDEX(Aplicacoes!$G$3:$G$1002,MATCH(20,Aplicacoes!$J$3:$J$1002,0)),"")
A44: =IFERROR(INDEX(Aplicacoes!$C$3:$C$1002,MATCH(21,Aplicacoes!$J$3:$J$1002,0)),"") | B44: =IFERROR(INDEX(Aplicacoes!$D$3:$D$1002,MATCH(21,Aplicacoes!$J$3:$J$1002,0)),"") | C44: =IFERROR(INDEX(Aplicacoes!$E$3:$E$1002,MATCH(21,Aplicacoes!$J$3:$J$1002,0)),"") | D44: =IFERROR(INDEX(Aplicacoes!$F$3:$F$1002,MATCH(21,Aplicacoes!$J$3:$J$1002,0)),"") | E44: =IFERROR(INDEX(Aplicacoes!$F$3:$F$1002,MATCH(21,Aplicacoes!$J$3:$J$1002,0))/$B$6,"") | F44: =IFERROR(INDEX(Aplicacoes!$G$3:$G$1002,MATCH(21,Aplicacoes!$J$3:$J$1002,0)),"")
A45: =IFERROR(INDEX(Aplicacoes!$C$3:$C$1002,MATCH(22,Aplicacoes!$J$3:$J$1002,0)),"") | B45: =IFERROR(INDEX(Aplicacoes!$D$3:$D$1002,MATCH(22,Aplicacoes!$J$3:$J$1002,0)),"") | C45: =IFERROR(INDEX(Aplicacoes!$E$3:$E$1002,MATCH(22,Aplicacoes!$J$3:$J$1002,0)),"") | D45: =IFERROR(INDEX(Aplicacoes!$F$3:$F$1002,MATCH(22,Aplicacoes!$J$3:$J$1002,0)),"") | E45: =IFERROR(INDEX(Aplicacoes!$F$3:$F$1002,MATCH(22,Aplicacoes!$J$3:$J$1002,0))/$B$6,"") | F45: =IFERROR(INDEX(Aplicacoes!$G$3:$G$1002,MATCH(22,Aplicacoes!$J$3:$J$1002,0)),"")
A46: =IFERROR(INDEX(Aplicacoes!$C$3:$C$1002,MATCH(23,Aplicacoes!$J$3:$J$1002,0)),"") | B46: =IFERROR(INDEX(Aplicacoes!$D$3:$D$1002,MATCH(23,Aplicacoes!$J$3:$J$1002,0)),"") | C46: =IFERROR(INDEX(Aplicacoes!$E$3:$E$1002,MATCH(23,Aplicacoes!$J$3:$J$1002,0)),"") | D46: =IFERROR(INDEX(Aplicacoes!$F$3:$F$1002,MATCH(23,Aplicacoes!$J$3:$J$1002,0)),"") | E46: =IFERROR(INDEX(Aplicacoes!$F$3:$F$1002,MATCH(23,Aplicacoes!$J$3:$J$1002,0))/$B$6,"") | F46: =IFERROR(INDEX(Aplicacoes!$G$3:$G$1002,MATCH(23,Aplicacoes!$J$3:$J$1002,0)),"")
A47: =IFERROR(INDEX(Aplicacoes!$C$3:$C$1002,MATCH(24,Aplicacoes!$J$3:$J$1002,0)),"") | B47: =IFERROR(INDEX(Aplicacoes!$D$3:$D$1002,MATCH(24,Aplicacoes!$J$3:$J$1002,0)),"") | C47: =IFERROR(INDEX(Aplicacoes!$E$3:$E$1002,MATCH(24,Aplicacoes!$J$3:$J$1002,0)),"") | D47: =IFERROR(INDEX(Aplicacoes!$F$3:$F$1002,MATCH(24,Aplicacoes!$J$3:$J$1002,0)),"") | E47: =IFERROR(INDEX(Aplicacoes!$F$3:$F$1002,MATCH(24,Aplicacoes!$J$3:$J$1002,0))/$B$6,"") | F47: =IFERROR(INDEX(Aplicacoes!$G$3:$G$1002,MATCH(24,Aplicacoes!$J$3:$J$1002,0)),"")
A48: =IFERROR(INDEX(Aplicacoes!$C$3:$C$1002,MATCH(25,Aplicacoes!$J$3:$J$1002,0)),"") | B48: =IFERROR(INDEX(Aplicacoes!$D$3:$D$1002,MATCH(25,Aplicacoes!$J$3:$J$1002,0)),"") | C48: =IFERROR(INDEX(Aplicacoes!$E$3:$E$1002,MATCH(25,Aplicacoes!$J$3:$J$1002,0)),"") | D48: =IFERROR(INDEX(Aplicacoes!$F$3:$F$1002,MATCH(25,Aplicacoes!$J$3:$J$1002,0)),"") | E48: =IFERROR(INDEX(Aplicacoes!$F$3:$F$1002,MATCH(25,Aplicacoes!$J$3:$J$1002,0))/$B$6,"") | F48: =IFERROR(INDEX(Aplicacoes!$G$3:$G$1002,MATCH(25,Aplicacoes!$J$3:$J$1002,0)),"")
A49: =IFERROR(INDEX(Aplicacoes!$C$3:$C$1002,MATCH(26,Aplicacoes!$J$3:$J$1002,0)),"") | B49: =IFERROR(INDEX(Aplicacoes!$D$3:$D$1002,MATCH(26,Aplicacoes!$J$3:$J$1002,0)),"") | C49: =IFERROR(INDEX(Aplicacoes!$E$3:$E$1002,MATCH(26,Aplicacoes!$J$3:$J$1002,0)),"") | D49: =IFERROR(INDEX(Aplicacoes!$F$3:$F$1002,MATCH(26,Aplicacoes!$J$3:$J$1002,0)),"") | E49: =IFERROR(INDEX(Aplicacoes!$F$3:$F$1002,MATCH(26,Aplicacoes!$J$3:$J$1002,0))/$B$6,"") | F49: =IFERROR(INDEX(Aplicacoes!$G$3:$G$1002,MATCH(26,Aplicacoes!$J$3:$J$1002,0)),"")
A50: =IFERROR(INDEX(Aplicacoes!$C$3:$C$1002,MATCH(27,Aplicacoes!$J$3:$J$1002,0)),"") | B50: =IFERROR(INDEX(Aplicacoes!$D$3:$D$1002,MATCH(27,Aplicacoes!$J$3:$J$1002,0)),"") | C50: =IFERROR(INDEX(Aplicacoes!$E$3:$E$1002,MATCH(27,Aplicacoes!$J$3:$J$1002,0)),"") | D50: =IFERROR(INDEX(Aplicacoes!$F$3:$F$1002,MATCH(27,Aplicacoes!$J$3:$J$1002,0)),"") | E50: =IFERROR(INDEX(Aplicacoes!$F$3:$F$1002,MATCH(27,Aplicacoes!$J$3:$J$1002,0))/$B$6,"") | F50: =IFERROR(INDEX(Aplicacoes!$G$3:$G$1002,MATCH(27,Aplicacoes!$J$3:$J$1002,0)),"")
A51: =IFERROR(INDEX(Aplicacoes!$C$3:$C$1002,MATCH(28,Aplicacoes!$J$3:$J$1002,0)),"") | B51: =IFERROR(INDEX(Aplicacoes!$D$3:$D$1002,MATCH(28,Aplicacoes!$J$3:$J$1002,0)),"") | C51: =IFERROR(INDEX(Aplicacoes!$E$3:$E$1002,MATCH(28,Aplicacoes!$J$3:$J$1002,0)),"") | D51: =IFERROR(INDEX(Aplicacoes!$F$3:$F$1002,MATCH(28,Aplicacoes!$J$3:$J$1002,0)),"") | E51: =IFERROR(INDEX(Aplicacoes!$F$3:$F$1002,MATCH(28,Aplicacoes!$J$3:$J$1002,0))/$B$6,"") | F51: =IFERROR(INDEX(Aplicacoes!$G$3:$G$1002,MATCH(28,Aplicacoes!$J$3:$J$1002,0)),"")
A52: =IFERROR(INDEX(Aplicacoes!$C$3:$C$1002,MATCH(29,Aplicacoes!$J$3:$J$1002,0)),"") | B52: =IFERROR(INDEX(Aplicacoes!$D$3:$D$1002,MATCH(29,Aplicacoes!$J$3:$J$1002,0)),"") | C52: =IFERROR(INDEX(Aplicacoes!$E$3:$E$1002,MATCH(29,Aplicacoes!$J$3:$J$1002,0)),"") | D52: =IFERROR(INDEX(Aplicacoes!$F$3:$F$1002,MATCH(29,Aplicacoes!$J$3:$J$1002,0)),"") | E52: =IFERROR(INDEX(Aplicacoes!$F$3:$F$1002,MATCH(29,Aplicacoes!$J$3:$J$1002,0))/$B$6,"") | F52: =IFERROR(INDEX(Aplicacoes!$G$3:$G$1002,MATCH(29,Aplicacoes!$J$3:$J$1002,0)),"")
A53: =IFERROR(INDEX(Aplicacoes!$C$3:$C$1002,MATCH(30,Aplicacoes!$J$3:$J$1002,0)),"") | B53: =IFERROR(INDEX(Aplicacoes!$D$3:$D$1002,MATCH(30,Aplicacoes!$J$3:$J$1002,0)),"") | C53: =IFERROR(INDEX(Aplicacoes!$E$3:$E$1002,MATCH(30,Aplicacoes!$J$3:$J$1002,0)),"") | D53: =IFERROR(INDEX(Aplicacoes!$F$3:$F$1002,MATCH(30,Aplicacoes!$J$3:$J$1002,0)),"") | E53: =IFERROR(INDEX(Aplicacoes!$F$3:$F$1002,MATCH(30,Aplicacoes!$J$3:$J$1002,0))/$B$6,"") | F53: =IFERROR(INDEX(Aplicacoes!$G$3:$G$1002,MATCH(30,Aplicacoes!$J$3:$J$1002,0)),"")
A54: =IFERROR(INDEX(Aplicacoes!$C$3:$C$1002,MATCH(31,Aplicacoes!$J$3:$J$1002,0)),"") | B54: =IFERROR(INDEX(Aplicacoes!$D$3:$D$1002,MATCH(31,Aplicacoes!$J$3:$J$1002,0)),"") | C54: =IFERROR(INDEX(Aplicacoes!$E$3:$E$1002,MATCH(31,Aplicacoes!$J$3:$J$1002,0)),"") | D54: =IFERROR(INDEX(Aplicacoes!$F$3:$F$1002,MATCH(31,Aplicacoes!$J$3:$J$1002,0)),"") | E54: =IFERROR(INDEX(Aplicacoes!$F$3:$F$1002,MATCH(31,Aplicacoes!$J$3:$J$1002,0))/$B$6,"") | F54: =IFERROR(INDEX(Aplicacoes!$G$3:$G$1002,MATCH(31,Aplicacoes!$J$3:$J$1002,0)),"")
A55: =IFERROR(INDEX(Aplicacoes!$C$3:$C$1002,MATCH(32,Aplicacoes!$J$3:$J$1002,0)),"") | B55: =IFERROR(INDEX(Aplicacoes!$D$3:$D$1002,MATCH(32,Aplicacoes!$J$3:$J$1002,0)),"") | C55: =IFERROR(INDEX(Aplicacoes!$E$3:$E$1002,MATCH(32,Aplicacoes!$J$3:$J$1002,0)),"") | D55: =IFERROR(INDEX(Aplicacoes!$F$3:$F$1002,MATCH(32,Aplicacoes!$J$3:$J$1002,0)),"") | E55: =IFERROR(INDEX(Aplicacoes!$F$3:$F$1002,MATCH(32,Aplicacoes!$J$3:$J$1002,0))/$B$6,"") | F55: =IFERROR(INDEX(Aplicacoes!$G$3:$G$1002,MATCH(32,Aplicacoes!$J$3:$J$1002,0)),"")
A56: =IFERROR(INDEX(Aplicacoes!$C$3:$C$1002,MATCH(33,Aplicacoes!$J$3:$J$1002,0)),"") | B56: =IFERROR(INDEX(Aplicacoes!$D$3:$D$1002,MATCH(33,Aplicacoes!$J$3:$J$1002,0)),"") | C56: =IFERROR(INDEX(Aplicacoes!$E$3:$E$1002,MATCH(33,Aplicacoes!$J$3:$J$1002,0)),"") | D56: =IFERROR(INDEX(Aplicacoes!$F$3:$F$1002,MATCH(33,Aplicacoes!$J$3:$J$1002,0)),"") | E56: =IFERROR(INDEX(Aplicacoes!$F$3:$F$1002,MATCH(33,Aplicacoes!$J$3:$J$1002,0))/$B$6,"") | F56: =IFERROR(INDEX(Aplicacoes!$G$3:$G$1002,MATCH(33,Aplicacoes!$J$3:$J$1002,0)),"")
A57: =IFERROR(INDEX(Aplicacoes!$C$3:$C$1002,MATCH(34,Aplicacoes!$J$3:$J$1002,0)),"") | B57: =IFERROR(INDEX(Aplicacoes!$D$3:$D$1002,MATCH(34,Aplicacoes!$J$3:$J$1002,0)),"") | C57: =IFERROR(INDEX(Aplicacoes!$E$3:$E$1002,MATCH(34,Aplicacoes!$J$3:$J$1002,0)),"") | D57: =IFERROR(INDEX(Aplicacoes!$F$3:$F$1002,MATCH(34,Aplicacoes!$J$3:$J$1002,0)),"") | E57: =IFERROR(INDEX(Aplicacoes!$F$3:$F$1002,MATCH(34,Aplicacoes!$J$3:$J$1002,0))/$B$6,"") | F57: =IFERROR(INDEX(Aplicacoes!$G$3:$G$1002,MATCH(34,Aplicacoes!$J$3:$J$1002,0)),"")
A58: =IFERROR(INDEX(Aplicacoes!$C$3:$C$1002,MATCH(35,Aplicacoes!$J$3:$J$1002,0)),"") | B58: =IFERROR(INDEX(Aplicacoes!$D$3:$D$1002,MATCH(35,Aplicacoes!$J$3:$J$1002,0)),"") | C58: =IFERROR(INDEX(Aplicacoes!$E$3:$E$1002,MATCH(35,Aplicacoes!$J$3:$J$1002,0)),"") | D58: =IFERROR(INDEX(Aplicacoes!$F$3:$F$1002,MATCH(35,Aplicacoes!$J$3:$J$1002,0)),"") | E58: =IFERROR(INDEX(Aplicacoes!$F$3:$F$1002,MATCH(35,Aplicacoes!$J$3:$J$1002,0))/$B$6,"") | F58: =IFERROR(INDEX(Aplicacoes!$G$3:$G$1002,MATCH(35,Aplicacoes!$J$3:$J$1002,0)),"")
A59: =IFERROR(INDEX(Aplicacoes!$C$3:$C$1002,MATCH(36,Aplicacoes!$J$3:$J$1002,0)),"") | B59: =IFERROR(INDEX(Aplicacoes!$D$3:$D$1002,MATCH(36,Aplicacoes!$J$3:$J$1002,0)),"") | C59: =IFERROR(INDEX(Aplicacoes!$E$3:$E$1002,MATCH(36,Aplicacoes!$J$3:$J$1002,0)),"") | D59: =IFERROR(INDEX(Aplicacoes!$F$3:$F$1002,MATCH(36,Aplicacoes!$J$3:$J$1002,0)),"") | E59: =IFERROR(INDEX(Aplicacoes!$F$3:$F$1002,MATCH(36,Aplicacoes!$J$3:$J$1002,0))/$B$6,"") | F59: =IFERROR(INDEX(Aplicacoes!$G$3:$G$1002,MATCH(36,Aplicacoes!$J$3:$J$1002,0)),"")
A60: =IFERROR(INDEX(Aplicacoes!$C$3:$C$1002,MATCH(37,Aplicacoes!$J$3:$J$1002,0)),"") | B60: =IFERROR(INDEX(Aplicacoes!$D$3:$D$1002,MATCH(37,Aplicacoes!$J$3:$J$1002,0)),"") | C60: =IFERROR(INDEX(Aplicacoes!$E$3:$E$1002,MATCH(37,Aplicacoes!$J$3:$J$1002,0)),"") | D60: =IFERROR(INDEX(Aplicacoes!$F$3:$F$1002,MATCH(37,Aplicacoes!$J$3:$J$1002,0)),"") | E60: =IFERROR(INDEX(Aplicacoes!$F$3:$F$1002,MATCH(37,Aplicacoes!$J$3:$J$1002,0))/$B$6,"") | F60: =IFERROR(INDEX(Aplicacoes!$G$3:$G$1002,MATCH(37,Aplicacoes!$J$3:$J$1002,0)),"")
A61: =IFERROR(INDEX(Aplicacoes!$C$3:$C$1002,MATCH(38,Aplicacoes!$J$3:$J$1002,0)),"") | B61: =IFERROR(INDEX(Aplicacoes!$D$3:$D$1002,MATCH(38,Aplicacoes!$J$3:$J$1002,0)),"") | C61: =IFERROR(INDEX(Aplicacoes!$E$3:$E$1002,MATCH(38,Aplicacoes!$J$3:$J$1002,0)),"") | D61: =IFERROR(INDEX(Aplicacoes!$F$3:$F$1002,MATCH(38,Aplicacoes!$J$3:$J$1002,0)),"") | E61: =IFERROR(INDEX(Aplicacoes!$F$3:$F$1002,MATCH(38,Aplicacoes!$J$3:$J$1002,0))/$B$6,"") | F61: =IFERROR(INDEX(Aplicacoes!$G$3:$G$1002,MATCH(38,Aplicacoes!$J$3:$J$1002,0)),"")
A62: =IFERROR(INDEX(Aplicacoes!$C$3:$C$1002,MATCH(39,Aplicacoes!$J$3:$J$1002,0)),"") | B62: =IFERROR(INDEX(Aplicacoes!$D$3:$D$1002,MATCH(39,Aplicacoes!$J$3:$J$1002,0)),"") | C62: =IFERROR(INDEX(Aplicacoes!$E$3:$E$1002,MATCH(39,Aplicacoes!$J$3:$J$1002,0)),"") | D62: =IFERROR(INDEX(Aplicacoes!$F$3:$F$1002,MATCH(39,Aplicacoes!$J$3:$J$1002,0)),"") | E62: =IFERROR(INDEX(Aplicacoes!$F$3:$F$1002,MATCH(39,Aplicacoes!$J$3:$J$1002,0))/$B$6,"") | F62: =IFERROR(INDEX(Aplicacoes!$G$3:$G$1002,MATCH(39,Aplicacoes!$J$3:$J$1002,0)),"")
A63: =IFERROR(INDEX(Aplicacoes!$C$3:$C$1002,MATCH(40,Aplicacoes!$J$3:$J$1002,0)),"") | B63: =IFERROR(INDEX(Aplicacoes!$D$3:$D$1002,MATCH(40,Aplicacoes!$J$3:$J$1002,0)),"") | C63: =IFERROR(INDEX(Aplicacoes!$E$3:$E$1002,MATCH(40,Aplicacoes!$J$3:$J$1002,0)),"") | D63: =IFERROR(INDEX(Aplicacoes!$F$3:$F$1002,MATCH(40,Aplicacoes!$J$3:$J$1002,0)),"") | E63: =IFERROR(INDEX(Aplicacoes!$F$3:$F$1002,MATCH(40,Aplicacoes!$J$3:$J$1002,0))/$B$6,"") | F63: =IFERROR(INDEX(Aplicacoes!$G$3:$G$1002,MATCH(40,Aplicacoes!$J$3:$J$1002,0)),"")
A64: =IFERROR(INDEX(Aplicacoes!$C$3:$C$1002,MATCH(41,Aplicacoes!$J$3:$J$1002,0)),"") | B64: =IFERROR(INDEX(Aplicacoes!$D$3:$D$1002,MATCH(41,Aplicacoes!$J$3:$J$1002,0)),"") | C64: =IFERROR(INDEX(Aplicacoes!$E$3:$E$1002,MATCH(41,Aplicacoes!$J$3:$J$1002,0)),"") | D64: =IFERROR(INDEX(Aplicacoes!$F$3:$F$1002,MATCH(41,Aplicacoes!$J$3:$J$1002,0)),"") | E64: =IFERROR(INDEX(Aplicacoes!$F$3:$F$1002,MATCH(41,Aplicacoes!$J$3:$J$1002,0))/$B$6,"") | F64: =IFERROR(INDEX(Aplicacoes!$G$3:$G$1002,MATCH(41,Aplicacoes!$J$3:$J$1002,0)),"")
A65: =IFERROR(INDEX(Aplicacoes!$C$3:$C$1002,MATCH(42,Aplicacoes!$J$3:$J$1002,0)),"") | B65: =IFERROR(INDEX(Aplicacoes!$D$3:$D$1002,MATCH(42,Aplicacoes!$J$3:$J$1002,0)),"") | C65: =IFERROR(INDEX(Aplicacoes!$E$3:$E$1002,MATCH(42,Aplicacoes!$J$3:$J$1002,0)),"") | D65: =IFERROR(INDEX(Aplicacoes!$F$3:$F$1002,MATCH(42,Aplicacoes!$J$3:$J$1002,0)),"") | E65: =IFERROR(INDEX(Aplicacoes!$F$3:$F$1002,MATCH(42,Aplicacoes!$J$3:$J$1002,0))/$B$6,"") | F65: =IFERROR(INDEX(Aplicacoes!$G$3:$G$1002,MATCH(42,Aplicacoes!$J$3:$J$1002,0)),"")
A66: =IFERROR(INDEX(Aplicacoes!$C$3:$C$1002,MATCH(43,Aplicacoes!$J$3:$J$1002,0)),"") | B66: =IFERROR(INDEX(Aplicacoes!$D$3:$D$1002,MATCH(43,Aplicacoes!$J$3:$J$1002,0)),"") | C66: =IFERROR(INDEX(Aplicacoes!$E$3:$E$1002,MATCH(43,Aplicacoes!$J$3:$J$1002,0)),"") | D66: =IFERROR(INDEX(Aplicacoes!$F$3:$F$1002,MATCH(43,Aplicacoes!$J$3:$J$1002,0)),"") | E66: =IFERROR(INDEX(Aplicacoes!$F$3:$F$1002,MATCH(43,Aplicacoes!$J$3:$J$1002,0))/$B$6,"") | F66: =IFERROR(INDEX(Aplicacoes!$G$3:$G$1002,MATCH(43,Aplicacoes!$J$3:$J$1002,0)),"")
A67: =IFERROR(INDEX(Aplicacoes!$C$3:$C$1002,MATCH(44,Aplicacoes!$J$3:$J$1002,0)),"") | B67: =IFERROR(INDEX(Aplicacoes!$D$3:$D$1002,MATCH(44,Aplicacoes!$J$3:$J$1002,0)),"") | C67: =IFERROR(INDEX(Aplicacoes!$E$3:$E$1002,MATCH(44,Aplicacoes!$J$3:$J$1002,0)),"") | D67: =IFERROR(INDEX(Aplicacoes!$F$3:$F$1002,MATCH(44,Aplicacoes!$J$3:$J$1002,0)),"") | E67: =IFERROR(INDEX(Aplicacoes!$F$3:$F$1002,MATCH(44,Aplicacoes!$J$3:$J$1002,0))/$B$6,"") | F67: =IFERROR(INDEX(Aplicacoes!$G$3:$G$1002,MATCH(44,Aplicacoes!$J$3:$J$1002,0)),"")
A68: =IFERROR(INDEX(Aplicacoes!$C$3:$C$1002,MATCH(45,Aplicacoes!$J$3:$J$1002,0)),"") | B68: =IFERROR(INDEX(Aplicacoes!$D$3:$D$1002,MATCH(45,Aplicacoes!$J$3:$J$1002,0)),"") | C68: =IFERROR(INDEX(Aplicacoes!$E$3:$E$1002,MATCH(45,Aplicacoes!$J$3:$J$1002,0)),"") | D68: =IFERROR(INDEX(Aplicacoes!$F$3:$F$1002,MATCH(45,Aplicacoes!$J$3:$J$1002,0)),"") | E68: =IFERROR(INDEX(Aplicacoes!$F$3:$F$1002,MATCH(45,Aplicacoes!$J$3:$J$1002,0))/$B$6,"") | F68: =IFERROR(INDEX(Aplicacoes!$G$3:$G$1002,MATCH(45,Aplicacoes!$J$3:$J$1002,0)),"")
A69: =IFERROR(INDEX(Aplicacoes!$C$3:$C$1002,MATCH(46,Aplicacoes!$J$3:$J$1002,0)),"") | B69: =IFERROR(INDEX(Aplicacoes!$D$3:$D$1002,MATCH(46,Aplicacoes!$J$3:$J$1002,0)),"") | C69: =IFERROR(INDEX(Aplicacoes!$E$3:$E$1002,MATCH(46,Aplicacoes!$J$3:$J$1002,0)),"") | D69: =IFERROR(INDEX(Aplicacoes!$F$3:$F$1002,MATCH(46,Aplicacoes!$J$3:$J$1002,0)),"") | E69: =IFERROR(INDEX(Aplicacoes!$F$3:$F$1002,MATCH(46,Aplicacoes!$J$3:$J$1002,0))/$B$6,"") | F69: =IFERROR(INDEX(Aplicacoes!$G$3:$G$1002,MATCH(46,Aplicacoes!$J$3:$J$1002,0)),"")
A70: =IFERROR(INDEX(Aplicacoes!$C$3:$C$1002,MATCH(47,Aplicacoes!$J$3:$J$1002,0)),"") | B70: =IFERROR(INDEX(Aplicacoes!$D$3:$D$1002,MATCH(47,Aplicacoes!$J$3:$J$1002,0)),"") | C70: =IFERROR(INDEX(Aplicacoes!$E$3:$E$1002,MATCH(47,Aplicacoes!$J$3:$J$1002,0)),"") | D70: =IFERROR(INDEX(Aplicacoes!$F$3:$F$1002,MATCH(47,Aplicacoes!$J$3:$J$1002,0)),"") | E70: =IFERROR(INDEX(Aplicacoes!$F$3:$F$1002,MATCH(47,Aplicacoes!$J$3:$J$1002,0))/$B$6,"") | F70: =IFERROR(INDEX(Aplicacoes!$G$3:$G$1002,MATCH(47,Aplicacoes!$J$3:$J$1002,0)),"")
A71: =IFERROR(INDEX(Aplicacoes!$C$3:$C$1002,MATCH(48,Aplicacoes!$J$3:$J$1002,0)),"") | B71: =IFERROR(INDEX(Aplicacoes!$D$3:$D$1002,MATCH(48,Aplicacoes!$J$3:$J$1002,0)),"") | C71: =IFERROR(INDEX(Aplicacoes!$E$3:$E$1002,MATCH(48,Aplicacoes!$J$3:$J$1002,0)),"") | D71: =IFERROR(INDEX(Aplicacoes!$F$3:$F$1002,MATCH(48,Aplicacoes!$J$3:$J$1002,0)),"") | E71: =IFERROR(INDEX(Aplicacoes!$F$3:$F$1002,MATCH(48,Aplicacoes!$J$3:$J$1002,0))/$B$6,"") | F71: =IFERROR(INDEX(Aplicacoes!$G$3:$G$1002,MATCH(48,Aplicacoes!$J$3:$J$1002,0)),"")
A72: =IFERROR(INDEX(Aplicacoes!$C$3:$C$1002,MATCH(49,Aplicacoes!$J$3:$J$1002,0)),"") | B72: =IFERROR(INDEX(Aplicacoes!$D$3:$D$1002,MATCH(49,Aplicacoes!$J$3:$J$1002,0)),"") | C72: =IFERROR(INDEX(Aplicacoes!$E$3:$E$1002,MATCH(49,Aplicacoes!$J$3:$J$1002,0)),"") | D72: =IFERROR(INDEX(Aplicacoes!$F$3:$F$1002,MATCH(49,Aplicacoes!$J$3:$J$1002,0)),"") | E72: =IFERROR(INDEX(Aplicacoes!$F$3:$F$1002,MATCH(49,Aplicacoes!$J$3:$J$1002,0))/$B$6,"") | F72: =IFERROR(INDEX(Aplicacoes!$G$3:$G$1002,MATCH(49,Aplicacoes!$J$3:$J$1002,0)),"")
A73: =IFERROR(INDEX(Aplicacoes!$C$3:$C$1002,MATCH(50,Aplicacoes!$J$3:$J$1002,0)),"") | B73: =IFERROR(INDEX(Aplicacoes!$D$3:$D$1002,MATCH(50,Aplicacoes!$J$3:$J$1002,0)),"") | C73: =IFERROR(INDEX(Aplicacoes!$E$3:$E$1002,MATCH(50,Aplicacoes!$J$3:$J$1002,0)),"") | D73: =IFERROR(INDEX(Aplicacoes!$F$3:$F$1002,MATCH(50,Aplicacoes!$J$3:$J$1002,0)),"") | E73: =IFERROR(INDEX(Aplicacoes!$F$3:$F$1002,MATCH(50,Aplicacoes!$J$3:$J$1002,0))/$B$6,"") | F73: =IFERROR(INDEX(Aplicacoes!$G$3:$G$1002,MATCH(50,Aplicacoes!$J$3:$J$1002,0)),"")
A74: =IFERROR(INDEX(Aplicacoes!$C$3:$C$1002,MATCH(51,Aplicacoes!$J$3:$J$1002,0)),"") | B74: =IFERROR(INDEX(Aplicacoes!$D$3:$D$1002,MATCH(51,Aplicacoes!$J$3:$J$1002,0)),"") | C74: =IFERROR(INDEX(Aplicacoes!$E$3:$E$1002,MATCH(51,Aplicacoes!$J$3:$J$1002,0)),"") | D74: =IFERROR(INDEX(Aplicacoes!$F$3:$F$1002,MATCH(51,Aplicacoes!$J$3:$J$1002,0)),"") | E74: =IFERROR(INDEX(Aplicacoes!$F$3:$F$1002,MATCH(51,Aplicacoes!$J$3:$J$1002,0))/$B$6,"") | F74: =IFERROR(INDEX(Aplicacoes!$G$3:$G$1002,MATCH(51,Aplicacoes!$J$3:$J$1002,0)),"")
A75: =IFERROR(INDEX(Aplicacoes!$C$3:$C$1002,MATCH(52,Aplicacoes!$J$3:$J$1002,0)),"") | B75: =IFERROR(INDEX(Aplicacoes!$D$3:$D$1002,MATCH(52,Aplicacoes!$J$3:$J$1002,0)),"") | C75: =IFERROR(INDEX(Aplicacoes!$E$3:$E$1002,MATCH(52,Aplicacoes!$J$3:$J$1002,0)),"") | D75: =IFERROR(INDEX(Aplicacoes!$F$3:$F$1002,MATCH(52,Aplicacoes!$J$3:$J$1002,0)),"") | E75: =IFERROR(INDEX(Aplicacoes!$F$3:$F$1002,MATCH(52,Aplicacoes!$J$3:$J$1002,0))/$B$6,"") | F75: =IFERROR(INDEX(Aplicacoes!$G$3:$G$1002,MATCH(52,Aplicacoes!$J$3:$J$1002,0)),"")
A76: =IFERROR(INDEX(Aplicacoes!$C$3:$C$1002,MATCH(53,Aplicacoes!$J$3:$J$1002,0)),"") | B76: =IFERROR(INDEX(Aplicacoes!$D$3:$D$1002,MATCH(53,Aplicacoes!$J$3:$J$1002,0)),"") | C76: =IFERROR(INDEX(Aplicacoes!$E$3:$E$1002,MATCH(53,Aplicacoes!$J$3:$J$1002,0)),"") | D76: =IFERROR(INDEX(Aplicacoes!$F$3:$F$1002,MATCH(53,Aplicacoes!$J$3:$J$1002,0)),"") | E76: =IFERROR(INDEX(Aplicacoes!$F$3:$F$1002,MATCH(53,Aplicacoes!$J$3:$J$1002,0))/$B$6,"") | F76: =IFERROR(INDEX(Aplicacoes!$G$3:$G$1002,MATCH(53,Aplicacoes!$J$3:$J$1002,0)),"")
A77: =IFERROR(INDEX(Aplicacoes!$C$3:$C$1002,MATCH(54,Aplicacoes!$J$3:$J$1002,0)),"") | B77: =IFERROR(INDEX(Aplicacoes!$D$3:$D$1002,MATCH(54,Aplicacoes!$J$3:$J$1002,0)),"") | C77: =IFERROR(INDEX(Aplicacoes!$E$3:$E$1002,MATCH(54,Aplicacoes!$J$3:$J$1002,0)),"") | D77: =IFERROR(INDEX(Aplicacoes!$F$3:$F$1002,MATCH(54,Aplicacoes!$J$3:$J$1002,0)),"") | E77: =IFERROR(INDEX(Aplicacoes!$F$3:$F$1002,MATCH(54,Aplicacoes!$J$3:$J$1002,0))/$B$6,"") | F77: =IFERROR(INDEX(Aplicacoes!$G$3:$G$1002,MATCH(54,Aplicacoes!$J$3:$J$1002,0)),"")
A78: =IFERROR(INDEX(Aplicacoes!$C$3:$C$1002,MATCH(55,Aplicacoes!$J$3:$J$1002,0)),"") | B78: =IFERROR(INDEX(Aplicacoes!$D$3:$D$1002,MATCH(55,Aplicacoes!$J$3:$J$1002,0)),"") | C78: =IFERROR(INDEX(Aplicacoes!$E$3:$E$1002,MATCH(55,Aplicacoes!$J$3:$J$1002,0)),"") | D78: =IFERROR(INDEX(Aplicacoes!$F$3:$F$1002,MATCH(55,Aplicacoes!$J$3:$J$1002,0)),"") | E78: =IFERROR(INDEX(Aplicacoes!$F$3:$F$1002,MATCH(55,Aplicacoes!$J$3:$J$1002,0))/$B$6,"") | F78: =IFERROR(INDEX(Aplicacoes!$G$3:$G$1002,MATCH(55,Aplicacoes!$J$3:$J$1002,0)),"")
A79: =IFERROR(INDEX(Aplicacoes!$C$3:$C$1002,MATCH(56,Aplicacoes!$J$3:$J$1002,0)),"") | B79: =IFERROR(INDEX(Aplicacoes!$D$3:$D$1002,MATCH(56,Aplicacoes!$J$3:$J$1002,0)),"") | C79: =IFERROR(INDEX(Aplicacoes!$E$3:$E$1002,MATCH(56,Aplicacoes!$J$3:$J$1002,0)),"") | D79: =IFERROR(INDEX(Aplicacoes!$F$3:$F$1002,MATCH(56,Aplicacoes!$J$3:$J$1002,0)),"") | E79: =IFERROR(INDEX(Aplicacoes!$F$3:$F$1002,MATCH(56,Aplicacoes!$J$3:$J$1002,0))/$B$6,"") | F79: =IFERROR(INDEX(Aplicacoes!$G$3:$G$1002,MATCH(56,Aplicacoes!$J$3:$J$1002,0)),"")
A80: =IFERROR(INDEX(Aplicacoes!$C$3:$C$1002,MATCH(57,Aplicacoes!$J$3:$J$1002,0)),"") | B80: =IFERROR(INDEX(Aplicacoes!$D$3:$D$1002,MATCH(57,Aplicacoes!$J$3:$J$1002,0)),"") | C80: =IFERROR(INDEX(Aplicacoes!$E$3:$E$1002,MATCH(57,Aplicacoes!$J$3:$J$1002,0)),"") | D80: =IFERROR(INDEX(Aplicacoes!$F$3:$F$1002,MATCH(57,Aplicacoes!$J$3:$J$1002,0)),"") | E80: =IFERROR(INDEX(Aplicacoes!$F$3:$F$1002,MATCH(57,Aplicacoes!$J$3:$J$1002,0))/$B$6,"") | F80: =IFERROR(INDEX(Aplicacoes!$G$3:$G$1002,MATCH(57,Aplicacoes!$J$3:$J$1002,0)),"")
A81: =IFERROR(INDEX(Aplicacoes!$C$3:$C$1002,MATCH(58,Aplicacoes!$J$3:$J$1002,0)),"") | B81: =IFERROR(INDEX(Aplicacoes!$D$3:$D$1002,MATCH(58,Aplicacoes!$J$3:$J$1002,0)),"") | C81: =IFERROR(INDEX(Aplicacoes!$E$3:$E$1002,MATCH(58,Aplicacoes!$J$3:$J$1002,0)),"") | D81: =IFERROR(INDEX(Aplicacoes!$F$3:$F$1002,MATCH(58,Aplicacoes!$J$3:$J$1002,0)),"") | E81: =IFERROR(INDEX(Aplicacoes!$F$3:$F$1002,MATCH(58,Aplicacoes!$J$3:$J$1002,0))/$B$6,"") | F81: =IFERROR(INDEX(Aplicacoes!$G$3:$G$1002,MATCH(58,Aplicacoes!$J$3:$J$1002,0)),"")
A82: =IFERROR(INDEX(Aplicacoes!$C$3:$C$1002,MATCH(59,Aplicacoes!$J$3:$J$1002,0)),"") | B82: =IFERROR(INDEX(Aplicacoes!$D$3:$D$1002,MATCH(59,Aplicacoes!$J$3:$J$1002,0)),"") | C82: =IFERROR(INDEX(Aplicacoes!$E$3:$E$1002,MATCH(59,Aplicacoes!$J$3:$J$1002,0)),"") | D82: =IFERROR(INDEX(Aplicacoes!$F$3:$F$1002,MATCH(59,Aplicacoes!$J$3:$J$1002,0)),"") | E82: =IFERROR(INDEX(Aplicacoes!$F$3:$F$1002,MATCH(59,Aplicacoes!$J$3:$J$1002,0))/$B$6,"") | F82: =IFERROR(INDEX(Aplicacoes!$G$3:$G$1002,MATCH(59,Aplicacoes!$J$3:$J$1002,0)),"")
A83: =IFERROR(INDEX(Aplicacoes!$C$3:$C$1002,MATCH(60,Aplicacoes!$J$3:$J$1002,0)),"") | B83: =IFERROR(INDEX(Aplicacoes!$D$3:$D$1002,MATCH(60,Aplicacoes!$J$3:$J$1002,0)),"") | C83: =IFERROR(INDEX(Aplicacoes!$E$3:$E$1002,MATCH(60,Aplicacoes!$J$3:$J$1002,0)),"") | D83: =IFERROR(INDEX(Aplicacoes!$F$3:$F$1002,MATCH(60,Aplicacoes!$J$3:$J$1002,0)),"") | E83: =IFERROR(INDEX(Aplicacoes!$F$3:$F$1002,MATCH(60,Aplicacoes!$J$3:$J$1002,0))/$B$6,"") | F83: =IFERROR(INDEX(Aplicacoes!$G$3:$G$1002,MATCH(60,Aplicacoes!$J$3:$J$1002,0)),"")

Sheet Carteira Sugerida
A1: PROPOSTA DE CARTEIRA
A3: Cliente: | B3: ='Carteira do Cliente'!B3 | H3: PATRIMÔNIO PROPOSTO
A4: Patrimônio Atual: | B4: ='Carteira do Cliente'!B6 | H4: =SUM(E8:E32)
A6: CARTEIRA RECOMENDADA
A7: Classe | B7: Ativo sugerido | C7: Carência (dias corridos) | D7: Liquidez (D + dias) | E7: Valor (R$) | F7: % | Q7: Classe | R7: Valor | S7: D+ | T7: Valor
F8: =IFERROR($E8/SUM($E$8:$E$32),"") | Q8: ='Carteira do Cliente'!A11 | R8: =IF($Q8="",0,SUMIFS($E$8:$E$32,$A$8:$A$32,$Q8)) | S8: 0 | T8: =SUMIFS($E$8:$E$32,$D$8:$D$32,$S8)
F9: =IFERROR($E9/SUM($E$8:$E$32),"") | Q9: ='Carteira do Cliente'!A12 | R9: =IF($Q9="",0,SUMIFS($E$8:$E$32,$A$8:$A$32,$Q9)) | S9: 1 | T9: =SUMIFS($E$8:$E$32,$D$8:$D$32,$S9)
F10: =IFERROR($E10/SUM($E$8:$E$32),"") | Q10: ='Carteira do Cliente'!A13 | R10: =IF($Q10="",0,SUMIFS($E$8:$E$32,$A$8:$A$32,$Q10)) | S10: 10 | T10: =SUMIFS($E$8:$E$32,$D$8:$D$32,$S10)
F11: =IFERROR($E11/SUM($E$8:$E$32),"") | Q11: ='Carteira do Cliente'!A14 | R11: =IF($Q11="",0,SUMIFS($E$8:$E$32,$A$8:$A$32,$Q11)) | S11: 30 | T11: =SUMIFS($E$8:$E$32,$D$8:$D$32,$S11)
F12: =IFERROR($E12/SUM($E$8:$E$32),"") | Q12: ='Carteira do Cliente'!A15 | R12: =IF($Q12="",0,SUMIFS($E$8:$E$32,$A$8:$A$32,$Q12)) | S12: 45 | T12: =SUMIFS($E$8:$E$32,$D$8:$D$32,$S12)
F13: =IFERROR($E13/SUM($E$8:$E$32),"") | Q13: ='Carteira do Cliente'!A16 | R13: =IF($Q13="",0,SUMIFS($E$8:$E$32,$A$8:$A$32,$Q13)) | S13: 90 | T13: =SUMIFS($E$8:$E$32,$D$8:$D$32,$S13)
F14: =IFERROR($E14/SUM($E$8:$E$32),"") | Q14: ='Carteira do Cliente'!A17 | R14: =IF($Q14="",0,SUMIFS($E$8:$E$32,$A$8:$A$32,$Q14)) | S14: 180 | T14: =SUMIFS($E$8:$E$32,$D$8:$D$32,$S14)
F15: =IFERROR($E15/SUM($E$8:$E$32),"") | Q15: ='Carteira do Cliente'!A18 | R15: =IF($Q15="",0,SUMIFS($E$8:$E$32,$A$8:$A$32,$Q15)) | S15: 270 | T15: =SUMIFS($E$8:$E$32,$D$8:$D$32,$S15)
F16: =IFERROR($E16/SUM($E$8:$E$32),"") | S16: 365 | T16: =SUMIFS($E$8:$E$32,$D$8:$D$32,$S16)
F17: =IFERROR($E17/SUM($E$8:$E$32),"") | S17: 720 | T17: =SUMIFS($E$8:$E$32,$D$8:$D$32,$S17)
F18: =IFERROR($E18/SUM($E$8:$E$32),"") | S18: 1800 | T18: =SUMIFS($E$8:$E$32,$D$8:$D$32,$S18)
F19: =IFERROR($E19/SUM($E$8:$E$32),"")
F20: =IFERROR($E20/SUM($E$8:$E$32),"")
F21: =IFERROR($E21/SUM($E$8:$E$32),"")
F22: =IFERROR($E22/SUM($E$8:$E$32),"")
F23: =IFERROR($E23/SUM($E$8:$E$32),"")
F24: =IFERROR($E24/SUM($E$8:$E$32),"")
F25: =IFERROR($E25/SUM($E$8:$E$32),"")
F26: =IFERROR($E26/SUM($E$8:$E$32),"")
F27: =IFERROR($E27/SUM($E$8:$E$32),"")
F28: =IFERROR($E28/SUM($E$8:$E$32),"")
F29: =IFERROR($E29/SUM($E$8:$E$32),"")
F30: =IFERROR($E30/SUM($E$8:$E$32),"")
... F32: =IFERROR($E32/SUM($E$8:$E$32),"")
A33: TOTAL | E33: =SUM(E8:E32) | F33: =SUM(F8:F32)
A37: OTIMIZAÇÕES REALIZADAS
A44: RACIONAL POR MOVIMENTAÇÃO
A45: Ativo | B45: Racional (objetivo e justificativa)
A57: COMPARATIVO: ATUAL x SUGERIDA
A58: Classe | B58: % Atual | C58: % Sugerido | D58: Saldo Atual (R$) | E58: Valor Sugerido (R$) | F58: Diferença (R$) | G58: Ação
A59: ='Carteira do Cliente'!A11 | B59: ='Carteira do Cliente'!D11 | C59: =IFERROR($E59/SUM($E$8:$E$32),0) | D59: ='Carteira do Cliente'!C11 | E59: =SUMIFS($E$8:$E$32,$A$8:$A$32,$A59) | F59: =$E59-$D59 | G59: =IF(AND($D59=0,$E59=0),"",IF(ROUND($F59,2)>0,"Aumentar",IF(ROUND($F59,2)<0,"Reduzir","Manter")))
A60: ='Carteira do Cliente'!A12 | B60: ='Carteira do Cliente'!D12 | C60: =IFERROR($E60/SUM($E$8:$E$32),0) | D60: ='Carteira do Cliente'!C12 | E60: =SUMIFS($E$8:$E$32,$A$8:$A$32,$A60) | F60: =$E60-$D60 | G60: =IF(AND($D60=0,$E60=0),"",IF(ROUND($F60,2)>0,"Aumentar",IF(ROUND($F60,2)<0,"Reduzir","Manter")))
A61: ='Carteira do Cliente'!A13 | B61: ='Carteira do Cliente'!D13 | C61: =IFERROR($E61/SUM($E$8:$E$32),0) | D61: ='Carteira do Cliente'!C13 | E61: =SUMIFS($E$8:$E$32,$A$8:$A$32,$A61) | F61: =$E61-$D61 | G61: =IF(AND($D61=0,$E61=0),"",IF(ROUND($F61,2)>0,"Aumentar",IF(ROUND($F61,2)<0,"Reduzir","Manter")))
A62: ='Carteira do Cliente'!A14 | B62: ='Carteira do Cliente'!D14 | C62: =IFERROR($E62/SUM($E$8:$E$32),0) | D62: ='Carteira do Cliente'!C14 | E62: =SUMIFS($E$8:$E$32,$A$8:$A$32,$A62) | F62: =$E62-$D62 | G62: =IF(AND($D62=0,$E62=0),"",IF(ROUND($F62,2)>0,"Aumentar",IF(ROUND($F62,2)<0,"Reduzir","Manter")))
A63: ='Carteira do Cliente'!A15 | B63: ='Carteira do Cliente'!D15 | C63: =IFERROR($E63/SUM($E$8:$E$32),0) | D63: ='Carteira do Cliente'!C15 | E63: =SUMIFS($E$8:$E$32,$A$8:$A$32,$A63) | F63: =$E63-$D63 | G63: =IF(AND($D63=0,$E63=0),"",IF(ROUND($F63,2)>0,"Aumentar",IF(ROUND($F63,2)<0,"Reduzir","Manter")))
A64: ='Carteira do Cliente'!A16 | B64: ='Carteira do Cliente'!D16 | C64: =IFERROR($E64/SUM($E$8:$E$32),0) | D64: ='Carteira do Cliente'!C16 | E64: =SUMIFS($E$8:$E$32,$A$8:$A$32,$A64) | F64: =$E64-$D64 | G64: =IF(AND($D64=0,$E64=0),"",IF(ROUND($F64,2)>0,"Aumentar",IF(ROUND($F64,2)<0,"Reduzir","Manter")))
A65: ='Carteira do Cliente'!A17 | B65: ='Carteira do Cliente'!D17 | C65: =IFERROR($E65/SUM($E$8:$E$32),0) | D65: ='Carteira do Cliente'!C17 | E65: =SUMIFS($E$8:$E$32,$A$8:$A$32,$A65) | F65: =$E65-$D65 | G65: =IF(AND($D65=0,$E65=0),"",IF(ROUND($F65,2)>0,"Aumentar",IF(ROUND($F65,2)<0,"Reduzir","Manter")))
A66: ='Carteira do Cliente'!A18 | B66: ='Carteira do Cliente'!D18 | C66: =IFERROR($E66/SUM($E$8:$E$32),0) | D66: ='Carteira do Cliente'!C18 | E66: =SUMIFS($E$8:$E$32,$A$8:$A$32,$A66) | F66: =$E66-$D66 | G66: =IF(AND($D66=0,$E66=0),"",IF(ROUND($F66,2)>0,"Aumentar",IF(ROUND($F66,2)<0,"Reduzir","Manter")))
A67: TOTAL | D67: =SUM(D59:D66) | E67: =SUM(E59:E66) | F67: =SUM(F59:F66)

Sheet Planejamento
A1: PLANEJAMENTO FINANCEIRO & APOSENTADORIA
A3: Cliente: | B3: ='Carteira do Cliente'!B3
A5: INFORMAÇÕES GERAIS E PATRIMÔNIO ATUAL | D5: INFLAÇÃO, CDI, ALÍQUOTA IR E TAXA NOMINAL
A6: Idade atual (anos) | B6: 51 | D6: Inflação anual projetada | E6: 0.04
A7: Idade de aposentadoria (anos) | B7: 64 | D7: Alíquota de IR (sobre rendimentos) | E7: 0.15
A8: Expectativa de vida (anos) | B8: 90 | D8: Taxa CDI anual | E8: 0.1065
A9: Horizonte de produção/acumulação (anos) | B9: =B7-B6 | D9: % do CDI esperado (rentabilidade) | E9: 0.72
A10: Patrimônio líquido disponível (R$) | B10: 0 | D10: Taxa nominal anual bruta (calc) | E10: =E8*E9
A11: Aplicação mensal (Prev + Meta) (R$) | B11: 0 | D11: Taxa nominal anual líquida (calc) | E11: =E10*(1-E7)
A13: PREMISSAS DE APOSENTADORIA | D13: TAXA DE JUROS REAL
A14: Renda desejada na aposentadoria (R$ / mês) | B14: 0 | D14: Taxa real anual bruta | E14: =(1+E10)/(1+E6)-1
A15: Renda projetada do INSS (R$ / mês) | B15: 0 | D15: Taxa real anual líquida | E15: =(1+E11)/(1+E6)-1
A16: Outras fontes de renda (R$ / mês) | B16: 0 | D16: Taxa real anual líquida pós-aposentadoria | E16: 0.03
A17: Renda a sustentar pelo patrimônio (R$ / mês) | B17: =MAX(0,B14-B15-B16) | D17: Taxa real mensal líquida pós-aposentadoria | E17: =(1+E16)^(1/12)-1
A18: Renda a sustentar pelo patrimônio (R$ / ano) | B18: =B17*12
A20: APOSENTADORIA — VIVER DE RENDA (preservando) | D20: APOSENTADORIA — CONSUMO COM SUCESSÃO
A21: Patrimônio necessário na aposentadoria | B21: =IFERROR(B18/E16,0) | D21: Patrimônio de sucessão desejado (R$) | E21: 0
A22: Parcela mensal necessária a aplicar | B22: =IFERROR(-PMT(E17,B9*12,-B10,B21),0) | D22: Patrimônio necessário na aposentadoria | E22: =IFERROR(PV(E16,B8-B7,-B18,-E21),0)
D23: Parcela mensal necessária a aplicar | E23: =IFERROR(-PMT(E17,B9*12,-B10,E22),0)
A25: OBJETIVOS DE VIDA (1-6 anos)
A26: Projeto | B26: Valor hoje (R$) | D26: Acumulação projetada (R$) | E26: Anos
A27: Projetos 1-2 anos | B27: 0 | D27: =B27*(1+E10)^E27 | E27: 2
A28: Projetos 3-4 anos | B28: 0 | D28: =B28*(1+E10)^E28 | E28: 4
A29: Projetos 5-6 anos | B29: 0 | D29: =B29*(1+E10)^E29 | E29: 6
A30: Total de Projetos e Acumulação | B30: =SUM(B27:B29) | D30: =SUM(D27:D29)
G33: PROJEÇÃO PATRIMONIAL (em R$ reais de hoje)
G34: Ano | H34: Idade | I34: Saldo Real | J34: Viver de Renda
G35: 0 | H35: =B6+G35 | I35: =B10 | J35: =IF(H35<B7,NA(),B21)
G36: 1 | H36: =B6+G36 | I36: =IF(H36<=B7,I35*(1+E15)+B11*12,MAX(0,I35*(1+E16)-B18)) | J36: =IF(H36<B7,NA(),B21)
G37: 2 | H37: =B6+G37 | I37: =IF(H37<=B7,I36*(1+E15)+B11*12,MAX(0,I36*(1+E16)-B18)) | J37: =IF(H37<B7,NA(),B21)
G38: 3 | H38: =B6+G38 | I38: =IF(H38<=B7,I37*(1+E15)+B11*12,MAX(0,I37*(1+E16)-B18)) | J38: =IF(H38<B7,NA(),B21)
G39: 4 | H39: =B6+G39 | I39: =IF(H39<=B7,I38*(1+E15)+B11*12,MAX(0,I38*(1+E16)-B18)) | J39: =IF(H39<B7,NA(),B21)
G40: 5 | H40: =B6+G40 | I40: =IF(H40<=B7,I39*(1+E15)+B11*12,MAX(0,I39*(1+E16)-B18)) | J40: =IF(H40<B7,NA(),B21)
G41: 6 | H41: =B6+G41 | I41: =IF(H41<=B7,I40*(1+E15)+B11*12,MAX(0,I40*(1+E16)-B18)) | J41: =IF(H41<B7,NA(),B21)
G42: 7 | H42: =B6+G42 | I42: =IF(H42<=B7,I41*(1+E15)+B11*12,MAX(0,I41*(1+E16)-B18)) | J42: =IF(H42<B7,NA(),B21)
G43: 8 | H43: =B6+G43 | I43: =IF(H43<=B7,I42*(1+E15)+B11*12,MAX(0,I42*(1+E16)-B18)) | J43: =IF(H43<B7,NA(),B21)
G44: 9 | H44: =B6+G44 | I44: =IF(H44<=B7,I43*(1+E15)+B11*12,MAX(0,I43*(1+E16)-B18)) | J44: =IF(H44<B7,NA(),B21)
G45: 10 | H45: =B6+G45 | I45: =IF(H45<=B7,I44*(1+E15)+B11*12,MAX(0,I44*(1+E16)-B18)) | J45: =IF(H45<B7,NA(),B21)
G46: 11 | H46: =B6+G46 | I46: =IF(H46<=B7,I45*(1+E15)+B11*12,MAX(0,I45*(1+E16)-B18)) | J46: =IF(H46<B7,NA(),B21)
G47: 12 | H47: =B6+G47 | I47: =IF(H47<=B7,I46*(1+E15)+B11*12,MAX(0,I46*(1+E16)-B18)) | J47: =IF(H47<B7,NA(),B21)
G48: 13 | H48: =B6+G48 | I48: =IF(H48<=B7,I47*(1+E15)+B11*12,MAX(0,I47*(1+E16)-B18)) | J48: =IF(H48<B7,NA(),B21)
G49: 14 | H49: =B6+G49 | I49: =IF(H49<=B7,I48*(1+E15)+B11*12,MAX(0,I48*(1+E16)-B18)) | J49: =IF(H49<B7,NA(),B21)
G50: 15 | H50: =B6+G50 | I50: =IF(H50<=B7,I49*(1+E15)+B11*12,MAX(0,I49*(1+E16)-B18)) | J50: =IF(H50<B7,NA(),B21)
G51: 16 | H51: =B6+G51 | I51: =IF(H51<=B7,I50*(1+E15)+B11*12,MAX(0,I50*(1+E16)-B18)) | J51: =IF(H51<B7,NA(),B21)
G52: 17 | H52: =B6+G52 | I52: =IF(H52<=B7,I51*(1+E15)+B11*12,MAX(0,I51*(1+E16)-B18)) | J52: =IF(H52<B7,NA(),B21)
G53: 18 | H53: =B6+G53 | I53: =IF(H53<=B7,I52*(1+E15)+B11*12,MAX(0,I52*(1+E16)-B18)) | J53: =IF(H53<B7,NA(),B21)
G54: 19 | H54: =B6+G54 | I54: =IF(H54<=B7,I53*(1+E15)+B11*12,MAX(0,I53*(1+E16)-B18)) | J54: =IF(H54<B7,NA(),B21)
G55: 20 | H55: =B6+G55 | I55: =IF(H55<=B7,I54*(1+E15)+B11*12,MAX(0,I54*(1+E16)-B18)) | J55: =IF(H55<B7,NA(),B21)
G56: 21 | H56: =B6+G56 | I56: =IF(H56<=B7,I55*(1+E15)+B11*12,MAX(0,I55*(1+E16)-B18)) | J56: =IF(H56<B7,NA(),B21)
G57: 22 | H57: =B6+G57 | I57: =IF(H57<=B7,I56*(1+E15)+B11*12,MAX(0,I56*(1+E16)-B18)) | J57: =IF(H57<B7,NA(),B21)
G58: 23 | H58: =B6+G58 | I58: =IF(H58<=B7,I57*(1+E15)+B11*12,MAX(0,I57*(1+E16)-B18)) | J58: =IF(H58<B7,NA(),B21)
G59: 24 | H59: =B6+G59 | I59: =IF(H59<=B7,I58*(1+E15)+B11*12,MAX(0,I58*(1+E16)-B18)) | J59: =IF(H59<B7,NA(),B21)
G60: 25 | H60: =B6+G60 | I60: =IF(H60<=B7,I59*(1+E15)+B11*12,MAX(0,I59*(1+E16)-B18)) | J60: =IF(H60<B7,NA(),B21)
G61: 26 | H61: =B6+G61 | I61: =IF(H61<=B7,I60*(1+E15)+B11*12,MAX(0,I60*(1+E16)-B18)) | J61: =IF(H61<B7,NA(),B21)
G62: 27 | H62: =B6+G62 | I62: =IF(H62<=B7,I61*(1+E15)+B11*12,MAX(0,I61*(1+E16)-B18)) | J62: =IF(H62<B7,NA(),B21)
G63: 28 | H63: =B6+G63 | I63: =IF(H63<=B7,I62*(1+E15)+B11*12,MAX(0,I62*(1+E16)-B18)) | J63: =IF(H63<B7,NA(),B21)
G64: 29 | H64: =B6+G64 | I64: =IF(H64<=B7,I63*(1+E15)+B11*12,MAX(0,I63*(1+E16)-B18)) | J64: =IF(H64<B7,NA(),B21)
G65: 30 | H65: =B6+G65 | I65: =IF(H65<=B7,I64*(1+E15)+B11*12,MAX(0,I64*(1+E16)-B18)) | J65: =IF(H65<B7,NA(),B21)
G66: 31 | H66: =B6+G66 | I66: =IF(H66<=B7,I65*(1+E15)+B11*12,MAX(0,I65*(1+E16)-B18)) | J66: =IF(H66<B7,NA(),B21)
G67: 32 | H67: =B6+G67 | I67: =IF(H67<=B7,I66*(1+E15)+B11*12,MAX(0,I66*(1+E16)-B18)) | J67: =IF(H67<B7,NA(),B21)
G68: 33 | H68: =B6+G68 | I68: =IF(H68<=B7,I67*(1+E15)+B11*12,MAX(0,I67*(1+E16)-B18)) | J68: =IF(H68<B7,NA(),B21)
G69: 34 | H69: =B6+G69 | I69: =IF(H69<=B7,I68*(1+E15)+B11*12,MAX(0,I68*(1+E16)-B18)) | J69: =IF(H69<B7,NA(),B21)
G70: 35 | H70: =B6+G70 | I70: =IF(H70<=B7,I69*(1+E15)+B11*12,MAX(0,I69*(1+E16)-B18)) | J70: =IF(H70<B7,NA(),B21)
G71: 36 | H71: =B6+G71 | I71: =IF(H71<=B7,I70*(1+E15)+B11*12,MAX(0,I70*(1+E16)-B18)) | J71: =IF(H71<B7,NA(),B21)
G72: 37 | H72: =B6+G72 | I72: =IF(H72<=B7,I71*(1+E15)+B11*12,MAX(0,I71*(1+E16)-B18)) | J72: =IF(H72<B7,NA(),B21)
G73: 38 | H73: =B6+G73 | I73: =IF(H73<=B7,I72*(1+E15)+B11*12,MAX(0,I72*(1+E16)-B18)) | J73: =IF(H73<B7,NA(),B21)
G74: 39 | H74: =B6+G74 | I74: =IF(H74<=B7,I73*(1+E15)+B11*12,MAX(0,I73*(1+E16)-B18)) | J74: =IF(H74<B7,NA(),B21)

Sheet Tabela Periódica
A1: TABELA PERIÓDICA DOS INVESTIMENTOS — RETORNO ANUAL
A3: Índice / Classe | B3: 2017 | C3: 2018 | D3: 2019 | E3: 2020 | F3: 2021 | G3: 2022 | H3: 2023 | I3: 2024 | J3: Acumulado
A4: S&P 500 | J4: =IFERROR(PRODUCT(IF(ISNUMBER(B4:I4),1+B4:I4,1))-1,"")
A5: Euro Stoxx 50 | J5: =IFERROR(PRODUCT(IF(ISNUMBER(B5:I5),1+B5:I5,1))-1,"")
A6: Ibovespa | J6: =IFERROR(PRODUCT(IF(ISNUMBER(B6:I6),1+B6:I6,1))-1,"")
A7: IFIX | J7: =IFERROR(PRODUCT(IF(ISNUMBER(B7:I7),1+B7:I7,1))-1,"")
A8: IMA-B | J8: =IFERROR(PRODUCT(IF(ISNUMBER(B8:I8),1+B8:I8,1))-1,"")
A9: IRF-M | J9: =IFERROR(PRODUCT(IF(ISNUMBER(B9:I9),1+B9:I9,1))-1,"")
A10: IHFA | J10: =IFERROR(PRODUCT(IF(ISNUMBER(B10:I10),1+B10:I10,1))-1,"")
A11: CDI | J11: =IFERROR(PRODUCT(IF(ISNUMBER(B11:I11),1+B11:I11,1))-1,"")
A12: Dólar | J12: =IFERROR(PRODUCT(IF(ISNUMBER(B12:I12),1+B12:I12,1))-1,"")
A13: Inflação | J13: =IFERROR(PRODUCT(IF(ISNUMBER(B13:I13),1+B13:I13,1))-1,"")
A16: Preencha os retornos anuais (em %) de cada índice/classe. A coluna Acumulado é calculada automaticamente; a cor destaca os melhores (verde) e piores (vermelho) de cada ano.

Sheet Instruções
A1: COMO USAR ESTA PLANILHA
A3: 1. Aba 'Clientes': cadastre cada cliente uma única vez — Penumper, Nome e CPF. O Penumper é a chave que liga tudo; pode ter letras (ex.: 1297217A), por isso a coluna é formatada como texto.
A4: Penumper ou CPF repetidos ficam destacados em vermelho.
A6: 2. Aba 'Aplicacoes': cole aqui a posição vinda do sistema — Penumper, Mês, Produto, Subproduto, Vencimento, Saldo Ponta e Idade.
A7: As colunas Nome e CPF se preenchem sozinhas por PROCV usando o Penumper. Se aparecer 'NÃO CADASTRADO', falta cadastrar o cliente na aba 'Clientes'.
A8: Cada linha é um investimento (um produto/subproduto com saldo).
A10: 3. Aba 'Carteira do Cliente': escolha o cliente no menu suspenso. A planilha mostra o patrimônio total, a alocação por classe (com gráfico) e a lista das aplicações daquele cliente.
A11: A linha 'Não classificado' indica saldo cujo Produto não casou com nenhum filtro — ajuste os filtros da coluna B se isso acontecer.
A13: 4. Classes: na aba 'Carteira do Cliente' a coluna 'Filtro (contém)' define como cada classe é somada. Ex.: o filtro FUNDOS soma todo Produto que contenha 'FUNDOS'. Edite rótulos e filtros à vontade.
A15: 5. Aba 'Carteira Sugerida' (proposta): monte a carteira recomendada — Classe, Ativo sugerido, Carência (dias), Liquidez (dias) e Valor. O banner 'Patrimônio Proposto' soma sozinho e os dois gráficos (composição por classe e distribuição de liquidez) se atualizam.
A16: Logo abaixo há campos livres para você descrever as Otimizações Realizadas e o Racional por movimentação (objetivo, justificativa).
A17: O Comparativo no fim mostra, classe a classe, o % atual x o % sugerido e quanto Aumentar ou Reduzir.
... A23: Observação: a planilha trabalha com a posição atual (foto). Para acrescentar uma nova posição, basta colar mais linhas na aba 'Aplicacoes' — as fórmulas se estendem automaticamente.
